chparse/__init__.py
chparse/chart.py
chparse/flags.py
chparse/instrument.py
chparse/note.py
chparse/parse.py
chparse-0.0.3.dist-info/LICENSE
chparse-0.0.3.dist-info/METADATA
chparse-0.0.3.dist-info/WHEEL
chparse-0.0.3.dist-info/top_level.txt
chparse-0.0.3.dist-info/RECORD
