Metadata-Version: 1.2
Name: chparse
Version: 0.0.3
Summary: Parse Clone Hero charts with ease!.
Home-page: https://github.com/Kenny2github/chparse
Author: Ken Hilton
License: GPLv3+
Keywords: file format parser
Platform: UNKNOWN
Classifier: Development Status :: 4 - Beta
Classifier: Intended Audience :: Developers
Classifier: Topic :: Text Processing :: Markup
Classifier: License :: OSI Approved :: GNU General Public License v3 or later (GPLv3+)
Classifier: Programming Language :: Python :: 3.6
Classifier: Programming Language :: Python :: 3.7
Requires-Python: >=3.6
